CONTRIBUTORS
COPYING
MANIFEST.in
README.md
clone.py
setup.cfg
setup.py
osc_plugin_clone/__init__.py
osc_plugin_clone/main.py
osc_plugin_clone/progress.py
osc_plugin_clone.egg-info/PKG-INFO
osc_plugin_clone.egg-info/SOURCES.txt
osc_plugin_clone.egg-info/dependency_links.txt
osc_plugin_clone.egg-info/requires.txt
osc_plugin_clone.egg-info/top_level.txt