Metadata-Version: 2.1
Name: osc-plugin-clone
Version: 20170913.1
Summary: OSC plugin for cloning projects and forking distributions
Home-page: https://gitlab.collabora.com/andrewsh/osc-plugin-clone
Author: Andrej Shadura
Author-email: andrew.shadura@collabora.co.uk
License: GPL-2+
Platform: UNKNOWN
Classifier: Development Status :: 4 - Beta
Classifier: Environment :: Console
Classifier: Intended Audience :: Developers
Classifier: Intended Audience :: System Administrators
Classifier: License :: OSI Approved :: GNU General Public License (GPL)
Classifier: Operating System :: OS Independent
Classifier: Programming Language :: Python
Classifier: Programming Language :: Python :: 2.7
Classifier: Programming Language :: Python :: 3
Classifier: Topic :: Software Development :: Build Tools
Provides-Extra: progress
Provides-Extra: tests
